docagent/__init__.py
docagent/analyzer.py
docagent/cli.py
docagent/core.py
docagent/providers.py
llm_docagent-1.0.1.dist-info/METADATA
llm_docagent-1.0.1.dist-info/WHEEL
llm_docagent-1.0.1.dist-info/entry_points.txt
llm_docagent-1.0.1.dist-info/top_level.txt
llm_docagent-1.0.1.dist-info/RECORD
