Metadata-Version: 2.4
Name: llm-docagent
Version: 1.0.1
Summary: AI-powered documentation generator for code projects
Home-page: https://github.com//docagent
Author: Ansh Tyagi
Author-email: Ansh Tyagi <anshtyagi314159@gmail.com>
License: MIT
Project-URL: Homepage, https://github.com/Anshtyagi1729/DocAgent
Project-URL: BugReports, https://github.com/Anshtyagi1729/DocAgent
Project-URL: Source, https://github.com/Anshtyagi1729/DocAgent
Project-URL: Documentation, https://github.com/Anshtyagi1729/DocAgent#readme
Keywords: documentation,ai,llm,openai,huggingface,ollama,groq,code-analysis
Classifier: Development Status :: 4 - Beta
Classifier: Intended Audience :: Developers
Classifier: Topic :: Software Development :: Documentation
Classifier: Topic :: Software Development :: Libraries :: Python Modules
Classifier: License :: OSI Approved :: MIT License
Classifier: Programming Language :: Python :: 3
Classifier: Programming Language :: Python :: 3.7
Classifier: Programming Language :: Python :: 3.8
Classifier: Programming Language :: Python :: 3.9
Classifier: Programming Language :: Python :: 3.10
Classifier: Programming Language :: Python :: 3.11
Classifier: Programming Language :: Python :: 3.12
Classifier: Operating System :: OS Independent
Classifier: Environment :: Console
Requires-Python: >=3.7
Requires-Dist: requests>=2.25.0
Requires-Dist: python-dotenv>=0.19.0
Provides-Extra: dev
Requires-Dist: pytest>=6.0; extra == "dev"
Requires-Dist: pytest-cov>=2.0; extra == "dev"
Requires-Dist: black>=21.0; extra == "dev"
Requires-Dist: flake8>=3.9; extra == "dev"
Requires-Dist: twine>=3.0; extra == "dev"
Dynamic: author
Dynamic: home-page
Dynamic: requires-python
